wooordhunt_parser/__init__.py
wooordhunt_parser/constants.py
wooordhunt_parser/parsers.py
wooordhunt_parser/validators.py
wooordhunt_parser/word.py
wooordhunt_parser-0.4.4.dist-info/METADATA
wooordhunt_parser-0.4.4.dist-info/WHEEL
wooordhunt_parser-0.4.4.dist-info/RECORD
