Metadata-Version: 2.3
Name: wooordhunt-parser
Version: 0.4.4
Summary: 
Author: Sustavov Maksim
Author-email: maksim.sustavov@edgecenter.ru
Requires-Python: >=3.12,<3.13
Classifier: Programming Language :: Python :: 3
Classifier: Programming Language :: Python :: 3.12
Requires-Dist: beautifulsoup4 (>=4.12.3,<5.0.0)
Requires-Dist: httpx (>=0.28.1,<0.29.0)
Requires-Dist: lxml (>=5.3.0,<6.0.0)
Project-URL: Homepage, https://github.com/Maksonik/parser_WooordHunt
